{
  "project_info": {
    "project_number": "1026651677420",
    "project_id": "movieapp-81f29",
    "storage_bucket": "movieapp-81f29.appspot.com"
  },
  "client": [
    {
      "client_info": {
        "mobilesdk_app_id": "1:1026651677420:android:a7a35592ba56eec29cbbc9",
        "android_client_info": {
          "package_name": "com.example.grabb"
        }
      },
      "oauth_client": [
        {
          "client_id": "1026651677420-ubmndv3ha245ku6tet361597uv16f18l.apps.googleusercontent.com",
          "client_type": 1,
          "android_info": {
            "package_name": "com.example.grabb",
            "certificate_hash": "c5bfadfa81e7bc01533e27c704e4184e4bf4aeda"
          }
        },
        {
          "client_id": "1026651677420-70q7rihk2bchmnp6jph23i3moumpqrmc.apps.googleusercontent.com",
          "client_type": 3
        }
      ],
      "api_key": [
        {
          "current_key": "AIzaSyD3CbEe4dCmRvyn_fiVNhKv721H6HIlD5A"
        }
      ],
      "services": {
        "appinvite_service": {
          "other_platform_oauth_client": [
            {
              "client_id": "1026651677420-70q7rihk2bchmnp6jph23i3moumpqrmc.apps.googleusercontent.com",
              "client_type": 3
            }
          ]
        }
      }
    }
  ],
  "configuration_version": "1"
}